dissert_helper_functions_ksu_peter/__init__.py
dissert_helper_functions_ksu_peter/checkers.py
dissert_helper_functions_ksu_peter/helpers.py
dissert_helper_functions_ksu_peter/stats_functions.py
dissert_helper_functions_ksu_peter-0.0.6.dist-info/LICENSE
dissert_helper_functions_ksu_peter-0.0.6.dist-info/METADATA
dissert_helper_functions_ksu_peter-0.0.6.dist-info/WHEEL
dissert_helper_functions_ksu_peter-0.0.6.dist-info/top_level.txt
dissert_helper_functions_ksu_peter-0.0.6.dist-info/RECORD
