Metadata-Version: 2.1
Name: dissert-helper-functions-ksu-peter
Version: 0.0.6
Summary: A small package with collection of useful functions for dissertation
Home-page: https://github.com/pomkos
Author: Peter Gates
Author-email: pgate89@gmail.com
License: MIT
Platform: UNKNOWN
Requires-Dist: numpy
Requires-Dist: scipy
Requires-Dist: pytz
Requires-Dist: sqlalchemy
Requires-Dist: pandas
Requires-Dist: matplotlib
Requires-Dist: seaborn
